riva_api/__init__.py
riva_api/package_info.py
riva_api-0.0.2.dist-info/LICENSE
riva_api-0.0.2.dist-info/METADATA
riva_api-0.0.2.dist-info/WHEEL
riva_api-0.0.2.dist-info/top_level.txt
riva_api-0.0.2.dist-info/RECORD
